{
  "version": "6.0",
  "nxVersion": "20.8.1",
  "pathMappings": {},
  "nxJsonPlugins": [],
  "pluginsConfig": {
    "@nx/js": {
      "analyzeSourceFiles": false
    }
  },
  "fileMap": {
    "projectFileMap": {
      "@design/react-components-input": [
        {
          "file": "packages/react/components/input/build.js",
          "hash": "14847324200671330000"
        },
        {
          "file": "packages/react/components/input/package.json",
          "hash": "15812345649605719577",
          "deps": [
            "@design/themes",
            "npm:react",
            "@design/esbuild-config",
            "@design/react-hooks-input",
            "npm:@types/react",
            "npm:@types/react-dom",
            "npm:@vanilla-extract/css",
            "npm:@vanilla-extract/dynamic",
            "npm:@vanilla-extract/esbuild-plugin",
            "npm:@vanilla-extract/recipes",
            "npm:@vanilla-extract/sprinkles",
            "npm:autoprefixer",
            "npm:postcss",
            "npm:react-dom",
            "npm:typescript",
            "npm:clsx"
          ]
        },
        {
          "file": "packages/react/components/input/src/Input.tsx",
          "hash": "16510842033983149334"
        },
        {
          "file": "packages/react/components/input/src/index.ts",
          "hash": "9083214782616530803"
        },
        {
          "file": "packages/react/components/input/src/style.css.ts",
          "hash": "9801428659691445812"
        },
        {
          "file": "packages/react/components/input/src/types.ts",
          "hash": "9086517983920486933"
        },
        {
          "file": "packages/react/components/input/tsconfig.json",
          "hash": "10344179325425879767"
        }
      ],
      "@design/react-components-layout": [
        {
          "file": "packages/react/components/layout/build.js",
          "hash": "14847324200671330000"
        },
        {
          "file": "packages/react/components/layout/package.json",
          "hash": "9648328345856865069",
          "deps": [
            "@design/themes",
            "npm:react",
            "@design/esbuild-config",
            "npm:@types/react",
            "npm:@types/react-dom",
            "npm:@vanilla-extract/css",
            "npm:@vanilla-extract/esbuild-plugin",
            "npm:@vanilla-extract/recipes",
            "npm:@vanilla-extract/sprinkles",
            "npm:autoprefixer",
            "npm:postcss",
            "npm:react-dom",
            "npm:typescript",
            "npm:clsx"
          ]
        },
        {
          "file": "packages/react/components/layout/src/core/style.css.ts",
          "hash": "5178472597711962396"
        },
        {
          "file": "packages/react/components/layout/src/core/types.ts",
          "hash": "11608835774093861949"
        },
        {
          "file": "packages/react/components/layout/src/index.ts",
          "hash": "6244142156080385606"
        },
        {
          "file": "packages/react/components/layout/src/layout/Box.tsx",
          "hash": "2850316510987021267"
        },
        {
          "file": "packages/react/components/layout/src/layout/Divider.tsx",
          "hash": "2439529319987288725"
        },
        {
          "file": "packages/react/components/layout/src/layout/Flex.tsx",
          "hash": "10081729534599810939"
        },
        {
          "file": "packages/react/components/layout/src/layout/Grid.tsx",
          "hash": "4302426638494581950"
        },
        {
          "file": "packages/react/components/layout/src/layout/GridItem.tsx",
          "hash": "17812383936832578858"
        },
        {
          "file": "packages/react/components/layout/src/layout/List.tsx",
          "hash": "10937415070200709031"
        },
        {
          "file": "packages/react/components/layout/src/layout/ListItem.tsx",
          "hash": "7740919160086565125"
        },
        {
          "file": "packages/react/components/layout/src/layout/OrderedList.tsx",
          "hash": "16160725697369494952"
        },
        {
          "file": "packages/react/components/layout/src/layout/UnorderedList.tsx",
          "hash": "6042355473494618970"
        },
        {
          "file": "packages/react/components/layout/src/layout/index.ts",
          "hash": "5774240188068120505"
        },
        {
          "file": "packages/react/components/layout/src/layout/types.ts",
          "hash": "11486561781907631971"
        },
        {
          "file": "packages/react/components/layout/src/typography/Heading.tsx",
          "hash": "1896566758865436495"
        },
        {
          "file": "packages/react/components/layout/src/typography/Text.tsx",
          "hash": "12628465776603456719"
        },
        {
          "file": "packages/react/components/layout/src/typography/index.ts",
          "hash": "462209517168200293"
        },
        {
          "file": "packages/react/components/layout/src/typography/style.css.ts",
          "hash": "1625234255959360224"
        },
        {
          "file": "packages/react/components/layout/src/typography/types.ts",
          "hash": "800209035478746864"
        },
        {
          "file": "packages/react/components/layout/src/utils/properties.ts",
          "hash": "5698855879563130366"
        },
        {
          "file": "packages/react/components/layout/tsconfig.json",
          "hash": "10344179325425879767"
        }
      ],
      "@design/react-hooks-input": [
        {
          "file": "packages/react/hooks/input/build.js",
          "hash": "11313241788351511933"
        },
        {
          "file": "packages/react/hooks/input/package.json",
          "hash": "10584200062201712423",
          "deps": [
            "npm:react",
            "@design/esbuild-config",
            "npm:@types/react",
            "npm:@types/react-dom",
            "npm:react-dom",
            "npm:typescript",
            "npm:clsx"
          ]
        },
        {
          "file": "packages/react/hooks/input/src/index.ts",
          "hash": "7663711916905442434"
        },
        {
          "file": "packages/react/hooks/input/src/types.ts",
          "hash": "12673548456480859685"
        },
        {
          "file": "packages/react/hooks/input/src/useInput.tsx",
          "hash": "14684169163763079917"
        },
        {
          "file": "packages/react/hooks/input/tsconfig.json",
          "hash": "10344179325425879767"
        }
      ],
      "@design/themes": [
        {
          "file": "packages/themes/build.js",
          "hash": "11313241788351511933"
        },
        {
          "file": "packages/themes/package.json",
          "hash": "15447323209807869585",
          "deps": [
            "@design/esbuild-config",
            "npm:typescript"
          ]
        },
        {
          "file": "packages/themes/scripts/build-css-module.js",
          "hash": "1209387752334535971"
        },
        {
          "file": "packages/themes/src/classes/index.ts",
          "hash": "14874153686921477232"
        },
        {
          "file": "packages/themes/src/classes/typography.ts",
          "hash": "4613592670763236173"
        },
        {
          "file": "packages/themes/src/index.ts",
          "hash": "5051740342712927388"
        },
        {
          "file": "packages/themes/src/variables/box.ts",
          "hash": "17415301785716516678"
        },
        {
          "file": "packages/themes/src/variables/colors/index.ts",
          "hash": "16067044052561609752"
        },
        {
          "file": "packages/themes/src/variables/colors/scale.ts",
          "hash": "7227875050283308958"
        },
        {
          "file": "packages/themes/src/variables/colors/static/dark.ts",
          "hash": "681337314988286385"
        },
        {
          "file": "packages/themes/src/variables/colors/static/index.ts",
          "hash": "17639848047638776056"
        },
        {
          "file": "packages/themes/src/variables/colors/static/light.ts",
          "hash": "5111065768491833496"
        },
        {
          "file": "packages/themes/src/variables/index.ts",
          "hash": "17288868138055620940"
        },
        {
          "file": "packages/themes/src/variables/typography.ts",
          "hash": "15749593622752628120"
        },
        {
          "file": "packages/themes/tsconfig.json",
          "hash": "10248009443664204963"
        }
      ],
      "@design/react-components-button": [
        {
          "file": "packages/react/components/button/build.js",
          "hash": "14847324200671330000"
        },
        {
          "file": "packages/react/components/button/package.json",
          "hash": "12530110280512217594",
          "deps": [
            "@design/themes",
            "npm:react",
            "@design/esbuild-config",
            "@design/react-hooks-button",
            "npm:@types/react",
            "npm:@types/react-dom",
            "npm:@vanilla-extract/css",
            "npm:@vanilla-extract/dynamic",
            "npm:@vanilla-extract/esbuild-plugin",
            "npm:@vanilla-extract/recipes",
            "npm:@vanilla-extract/sprinkles",
            "npm:autoprefixer",
            "npm:postcss",
            "npm:react-dom",
            "npm:typescript",
            "npm:clsx"
          ]
        },
        {
          "file": "packages/react/components/button/src/Button.tsx",
          "hash": "11618788357186952506"
        },
        {
          "file": "packages/react/components/button/src/index.ts",
          "hash": "8409040364927157818"
        },
        {
          "file": "packages/react/components/button/src/style.css.ts",
          "hash": "18283341336110057239"
        },
        {
          "file": "packages/react/components/button/src/types.ts",
          "hash": "10509118310460631555"
        },
        {
          "file": "packages/react/components/button/tsconfig.json",
          "hash": "10344179325425879767"
        }
      ],
      "@design/react-hooks-button": [
        {
          "file": "packages/react/hooks/button/build.js",
          "hash": "11313241788351511933"
        },
        {
          "file": "packages/react/hooks/button/package.json",
          "hash": "17257461162272477580",
          "deps": [
            "npm:react",
            "@design/esbuild-config",
            "@design/react-hooks-toggle",
            "npm:@types/react",
            "npm:@types/react-dom",
            "npm:react-dom",
            "npm:typescript",
            "npm:clsx"
          ]
        },
        {
          "file": "packages/react/hooks/button/src/index.ts",
          "hash": "10535575191923847207"
        },
        {
          "file": "packages/react/hooks/button/src/types.ts",
          "hash": "2574255652881697121"
        },
        {
          "file": "packages/react/hooks/button/src/useButton.tsx",
          "hash": "17027917869105670095"
        },
        {
          "file": "packages/react/hooks/button/src/useToggleButton.tsx",
          "hash": "4371948490279159530"
        },
        {
          "file": "packages/react/hooks/button/tsconfig.json",
          "hash": "10344179325425879767"
        }
      ],
      "@design/esbuild-config": [
        {
          "file": "packages/esbuild-config/README.md",
          "hash": "6886952344311067916"
        },
        {
          "file": "packages/esbuild-config/index.js",
          "hash": "219371835848018192"
        },
        {
          "file": "packages/esbuild-config/package.json",
          "hash": "5126038692030175162",
          "deps": [
            "npm:esbuild"
          ]
        }
      ],
      "@design/react-hooks-toggle": [
        {
          "file": "packages/react/hooks/toggle/build.js",
          "hash": "11313241788351511933"
        },
        {
          "file": "packages/react/hooks/toggle/package.json",
          "hash": "7527665168862678019",
          "deps": [
            "npm:react",
            "@design/esbuild-config",
            "npm:@types/react",
            "npm:@types/react-dom",
            "npm:react-dom",
            "npm:typescript",
            "npm:clsx"
          ]
        },
        {
          "file": "packages/react/hooks/toggle/src/index.ts",
          "hash": "13190166400749655539"
        },
        {
          "file": "packages/react/hooks/toggle/src/types.ts",
          "hash": "13666444803187522029"
        },
        {
          "file": "packages/react/hooks/toggle/src/useToggle.tsx",
          "hash": "9256311866014801661"
        },
        {
          "file": "packages/react/hooks/toggle/tsconfig.json",
          "hash": "10344179325425879767"
        }
      ],
      "@design/react-components-accordion": [
        {
          "file": "packages/react/components/accordion/build.js",
          "hash": "14847324200671330000"
        },
        {
          "file": "packages/react/components/accordion/package.json",
          "hash": "3095650003050820874",
          "deps": [
            "@design/themes",
            "npm:react",
            "@design/esbuild-config",
            "@design/react-hooks-button",
            "npm:@types/react",
            "npm:@types/react-dom",
            "npm:@vanilla-extract/css",
            "npm:@vanilla-extract/dynamic",
            "npm:@vanilla-extract/esbuild-plugin",
            "npm:@vanilla-extract/recipes",
            "npm:@vanilla-extract/sprinkles",
            "npm:autoprefixer",
            "npm:postcss",
            "npm:react-dom",
            "npm:typescript",
            "npm:clsx"
          ]
        },
        {
          "file": "packages/react/components/accordion/src/Accordion.tsx",
          "hash": "15257389082860536409"
        },
        {
          "file": "packages/react/components/accordion/src/AccordionButton.tsx",
          "hash": "13455860745340583345"
        },
        {
          "file": "packages/react/components/accordion/src/AccordionContext.tsx",
          "hash": "16134208989620431416"
        },
        {
          "file": "packages/react/components/accordion/src/AccordionItem.tsx",
          "hash": "18254717777939924557"
        },
        {
          "file": "packages/react/components/accordion/src/AccordionPanel.tsx",
          "hash": "13604674546571647425"
        },
        {
          "file": "packages/react/components/accordion/src/index.ts",
          "hash": "6692487404382574495"
        },
        {
          "file": "packages/react/components/accordion/src/style.css.ts",
          "hash": "6416636328336527355"
        },
        {
          "file": "packages/react/components/accordion/src/types.ts",
          "hash": "1779933654789481147"
        },
        {
          "file": "packages/react/components/accordion/tsconfig.json",
          "hash": "10344179325425879767"
        }
      ],
      "@design/storybook": [
        {
          "file": "services/storybook/.storybook/main.js",
          "hash": "4636232379943974874"
        },
        {
          "file": "services/storybook/.storybook/preview.js",
          "hash": "13967948772147123675"
        },
        {
          "file": "services/storybook/.storybook/vitest.setup.js",
          "hash": "12306884984581110654"
        },
        {
          "file": "services/storybook/README.md",
          "hash": "2624393197388313932"
        },
        {
          "file": "services/storybook/package.json",
          "hash": "1185938814449837256",
          "deps": [
            "npm:@chromatic-com/storybook",
            "@design/react-components-accordion",
            "@design/react-components-button",
            "@design/react-components-input",
            "@design/react-components-layout",
            "@design/react-hooks-button",
            "@design/themes",
            "npm:@storybook/addon-essentials",
            "npm:@storybook/addon-onboarding",
            "npm:@storybook/blocks",
            "npm:@storybook/experimental-addon-test",
            "npm:@storybook/react",
            "npm:@storybook/react-vite",
            "npm:@storybook/test",
            "npm:@vitest/browser",
            "npm:@vitest/coverage-v8",
            "npm:playwright",
            "npm:prop-types",
            "npm:storybook",
            "npm:storybook-addon-root-attributes",
            "npm:vite",
            "npm:vitest"
          ]
        },
        {
          "file": "services/storybook/stories/ReactComponents/Accordion/Accordion.stories.tsx",
          "hash": "1874287176436200776"
        },
        {
          "file": "services/storybook/stories/ReactComponents/Button/Button.stories.tsx",
          "hash": "4006079477454149112"
        },
        {
          "file": "services/storybook/stories/ReactComponents/Input/Input.stories.tsx",
          "hash": "4496806548143179944"
        },
        {
          "file": "services/storybook/stories/ReactComponents/Layout/Box.stories.tsx",
          "hash": "581852115420615072"
        },
        {
          "file": "services/storybook/stories/ReactComponents/Layout/Divider.stories.tsx",
          "hash": "8022903854489763433"
        },
        {
          "file": "services/storybook/stories/ReactComponents/Layout/Flex.stories.tsx",
          "hash": "7711119180040722455"
        },
        {
          "file": "services/storybook/stories/ReactComponents/Layout/List.stories.tsx",
          "hash": "17485686753674785470"
        },
        {
          "file": "services/storybook/stories/ReactComponents/Layout/Text.stories.tsx",
          "hash": "14400922439473532413"
        },
        {
          "file": "services/storybook/vitest.config.js",
          "hash": "13967297142312120885"
        }
      ]
    },
    "nonProjectFiles": [
      {
        "file": ".eslintrc.js",
        "hash": "14052870021940613983"
      },
      {
        "file": ".gitignore",
        "hash": "2615622172927270952"
      },
      {
        "file": ".prettierrc",
        "hash": "12078670118560183497"
      },
      {
        "file": ".yarn/releases/yarn-4.9.1.cjs",
        "hash": "3287485768833251469"
      },
      {
        "file": ".yarnrc.yml",
        "hash": "642009886735632000"
      },
      {
        "file": "README.md",
        "hash": "5283583518318966334"
      },
      {
        "file": "nx.json",
        "hash": "2802105145389868175"
      },
      {
        "file": "package.json",
        "hash": "3550945107969442348"
      },
      {
        "file": "tsconfig.base.json",
        "hash": "1179432164812416385"
      },
      {
        "file": "tsconfig.eslint.json",
        "hash": "9188420867814966836"
      },
      {
        "file": "yarn.lock",
        "hash": "18068794576541432277"
      }
    ]
  }
}